daipilot/__init__.py
daipilot/core.py
daipilot/database.py
daipilot/utils.py
daipilot/delete/__init__.py
daipilot/delete/main.py
daipilot/delete/realLife__1.py
daipilot/delete/task_func__1.py
daipilot/delete/tasks.py
daipilot/delete/utils.py
daipilot/reallife/__init__.py
daipilot/reallife/abstra.py
daipilot/reallife/cli.py
daipilot/reallife/core22.py
daipilot/reallife/execution_strategy.py
daipilot/reallife/workday_facade.py
daipilot/server/mcp/__init__.py
daipilot/server/mcp/prompt.py
daipilot/server/router/__init__.py
daipilot/server/router/tasks.py
daipilot-0.1.2.dist-info/METADATA
daipilot-0.1.2.dist-info/WHEEL
daipilot-0.1.2.dist-info/top_level.txt
daipilot-0.1.2.dist-info/RECORD
